LICENCE
README.md
setup.py
msaUtils/__init__.py
msaUtils/base_model.py
msaUtils/constants.py
msaUtils/email.py
msaUtils/errorhandling.py
msaUtils/file.py
msaUtils/fonts.py
msaUtils/gen_ref_pages.py
msaUtils/healthcheck.py
msaUtils/htmlutils.py
msaUtils/logger.py
msaUtils/profiler.py
msaUtils/scheduler.py
msaUtils/settings.py
msaUtils/sysinfo.py
msaUtils/token.py
msaUtils.egg-info/PKG-INFO
msaUtils.egg-info/SOURCES.txt
msaUtils.egg-info/dependency_links.txt
msaUtils.egg-info/top_level.txt
msaUtils.egg-info/zip-safe
msaUtils/models/__init__.py
msaUtils/models/files.py
msaUtils/models/health.py
msaUtils/models/scheduler.py