Metadata-Version: 2.1
Name: msaUtils
Version: 0.0.1
Summary: msaUtils - General utils for Microservices based on FastAPI like Profiler, Scheduler, Sysinfo, Healtcheck, Error Handling etc.
Home-page: https://github.com/swelcker/msaUtils
Download-URL: http://pypi.python.org/pypi/msaUtils
Author: Stefan Welcker
Author-email: stefan@u2d.ai
License: MIT
Project-URL: Documentation, http://msa.u2d.ai/
Project-URL: Source, https://github.com/swelcker/msaUtils
Project-URL: Tracker, https://github.com/swelcker/msaUtils/issues
Classifier: Development Status :: 4 - Beta
Classifier: Framework :: FastAPI
Classifier: Intended Audience :: Developers
Classifier: License :: OSI Approved :: MIT License
Classifier: Operating System :: MacOS :: MacOS X
Classifier: Operating System :: Microsoft :: Windows
Classifier: Operating System :: POSIX :: Linux
Classifier: Programming Language :: Python :: 3
Classifier: Programming Language :: Python :: 3.7
Classifier: Programming Language :: Python :: 3.8
Classifier: Programming Language :: Python :: 3.9
Classifier: Programming Language :: Python :: 3.10
Classifier: Topic :: Database
Classifier: Topic :: Database :: Front-Ends
Classifier: Topic :: Documentation
Classifier: Topic :: Internet :: WWW/HTTP :: WSGI :: Server
Classifier: Topic :: Software Development :: Libraries
Classifier: Topic :: Software Development :: Libraries :: Python Modules
License-File: LICENCE
